capybara/__init__.py
capybara/cpuinfo.py
capybara/enums.py
capybara/mixins.py
capybara/runtime.py
capybara/typing.py
capybara/onnxengine/__init__.py
capybara/onnxengine/engine.py
capybara/onnxengine/metadata.py
capybara/onnxengine/utils.py
capybara/openvinoengine/__init__.py
capybara/openvinoengine/engine.py
capybara/structures/__init__.py
capybara/structures/boxes.py
capybara/structures/functionals.py
capybara/structures/keypoints.py
capybara/structures/polygons.py
capybara/torchengine/__init__.py
capybara/torchengine/engine.py
capybara/utils/__init__.py
capybara/utils/custom_path.py
capybara/utils/custom_tqdm.py
capybara/utils/files_utils.py
capybara/utils/powerdict.py
capybara/utils/system_info.py
capybara/utils/time.py
capybara/utils/utils.py
capybara/vision/__init__.py
capybara/vision/functionals.py
capybara/vision/geometric.py
capybara/vision/improc.py
capybara/vision/morphology.py
capybara/vision/ipcam/__init__.py
capybara/vision/ipcam/app.py
capybara/vision/ipcam/camera.py
capybara/vision/ipcam/video_streaming.html
capybara/vision/videotools/__init__.py
capybara/vision/videotools/video2frames.py
capybara/vision/videotools/video2frames_v2.py
capybara/vision/visualization/__init__.py
capybara/vision/visualization/draw.py
capybara/vision/visualization/utils.py
capybara_docsaid-1.0.1.dist-info/licenses/LICENSE
capybara_docsaid-1.0.1.dist-info/METADATA
capybara_docsaid-1.0.1.dist-info/WHEEL
capybara_docsaid-1.0.1.dist-info/top_level.txt
capybara_docsaid-1.0.1.dist-info/RECORD
