Metadata-Version: 2.4
Name: capybara-docsaid
Version: 1.0.1
Summary: An Image Processing and Deep Learning Toolkit.
License: Apache License 2.0
Project-URL: Homepage, https://docsaid.org/en/docs/capybara/
Project-URL: Repository, https://github.com/DocsaidLab/Capybara
Project-URL: Issues, https://github.com/DocsaidLab/Capybara/issues
Classifier: Development Status :: 5 - Production/Stable
Classifier: License :: OSI Approved :: Apache Software License
Classifier: Intended Audience :: Developers
Classifier: Intended Audience :: Science/Research
Classifier: Operating System :: OS Independent
Classifier: Programming Language :: Python :: 3.10
Classifier: Programming Language :: Python :: 3.11
Classifier: Programming Language :: Python :: 3.12
Classifier: Programming Language :: Python :: 3.13
Classifier: Programming Language :: Python :: 3.14
Classifier: Topic :: Software Development :: Libraries
Classifier: Topic :: Software Development :: Libraries :: Python Modules
Requires-Python: >=3.10
License-File: LICENSE
Requires-Dist: dacite
Requires-Dist: requests
Requires-Dist: numpy
Requires-Dist: pdf2image
Requires-Dist: ujson
Requires-Dist: pyyaml
Requires-Dist: tqdm
Requires-Dist: pybase64
Requires-Dist: PyTurboJPEG
Requires-Dist: dill
Requires-Dist: natsort
Requires-Dist: shapely
Requires-Dist: piexif
Requires-Dist: opencv-python>=4.12.0.88
Requires-Dist: beautifulsoup4
Requires-Dist: pillow-heif
Provides-Extra: onnxruntime
Requires-Dist: onnxruntime<2,>=1.22.0; extra == "onnxruntime"
Requires-Dist: onnx>=1.18.0; extra == "onnxruntime"
Requires-Dist: onnxslim>=0.1.0; extra == "onnxruntime"
Provides-Extra: onnxruntime-gpu
Requires-Dist: onnxruntime-gpu<2,>=1.22.0; extra == "onnxruntime-gpu"
Requires-Dist: onnx>=1.18.0; extra == "onnxruntime-gpu"
Requires-Dist: onnxslim>=0.1.0; extra == "onnxruntime-gpu"
Provides-Extra: openvino
Requires-Dist: openvino>=2024.0.0; extra == "openvino"
Provides-Extra: torchscript
Requires-Dist: torch>=2.0; extra == "torchscript"
Provides-Extra: all
Requires-Dist: onnxruntime<2,>=1.22.0; extra == "all"
Requires-Dist: onnx>=1.18.0; extra == "all"
Requires-Dist: onnxslim>=0.1.0; extra == "all"
Requires-Dist: openvino>=2024.0.0; extra == "all"
Requires-Dist: torch>=2.0; extra == "all"
Provides-Extra: ipcam
Requires-Dist: flask>=2.0; extra == "ipcam"
Provides-Extra: system
Requires-Dist: psutil; extra == "system"
Provides-Extra: visualization
Requires-Dist: matplotlib; extra == "visualization"
Requires-Dist: pillow; extra == "visualization"
Dynamic: license-file
